cssinj/__init__.py
cssinj/__main__.py
cssinj/client.py
cssinj/console.py
cssinj/file.py
cssinj/exfiltrator/cssinjector.py
cssinj/exfiltrator/server.py
cssinj/strategies/__init__.py
cssinj/strategies/base.py
cssinj/strategies/complete.py
cssinj/strategies/fontface.py
cssinj/strategies/recursive.py
cssinj/utils/default.py
cssinj/utils/dom.py
cssinj/utils/error.py
cssinj-0.2.0.dist-info/licenses/LICENSE
cssinj-0.2.0.dist-info/METADATA
cssinj-0.2.0.dist-info/WHEEL
cssinj-0.2.0.dist-info/entry_points.txt
cssinj-0.2.0.dist-info/top_level.txt
cssinj-0.2.0.dist-info/RECORD
