Metadata-Version: 2.4
Name: cssinj
Version: 0.2.0
Summary: A python tools to exploits CSS injection vulnerabilities to exfiltrate sensitive information from web applications.
Author: DonAsako
License:                     GNU GENERAL PUBLIC LICENSE
Project-URL: Homepage, https://github.com/DonAsako/CSSinj
Project-URL: Issues, https://github.com/DonAsako/CSSinj/issues
Keywords: CSS,BugBounty,Web,cssinj
Classifier: Programming Language :: Python :: 3
Classifier: Programming Language :: Python :: 3 :: Only
Classifier: Operating System :: OS Independent
Classifier: License :: OSI Approved :: GNU General Public License v3 (GPLv3)
Requires-Python: >=3.10
License-File: LICENSE
Requires-Dist: aiohttp
Dynamic: license-file
